library_muhammad_osama_khan_x21242887/__init__.py
library_muhammad_osama_khan_x21242887/viewer_record.py
library_muhammad_osama_khan_x21242887-0.0.2.dist-info/METADATA
library_muhammad_osama_khan_x21242887-0.0.2.dist-info/WHEEL
library_muhammad_osama_khan_x21242887-0.0.2.dist-info/licenses/LICENSE
library_muhammad_osama_khan_x21242887-0.0.2.dist-info/RECORD
